{
  "parent": "minecraft:recipes/root",
  "rewards": {
    "recipes": [
      "furnish:gold_chair",
      "furnish:gold_coffee_table",
      "furnish:gold_couch",
      "furnish:gold_table"
    ]
  },
  "criteria": {
    "has_item": {
      "trigger": "minecraft:inventory_changed",
      "conditions": {
        "items": [
          {
            "item": "minecraft:gold_block"
          }
        ]
      }
    }
  },
  "requirements": [
    [
      "has_item"
    ]
  ]
}