{
    "forge_marker": 1,
    "defaults": {
        "textures": {
            "seat": "blocks/planks_jungle",
            "trim": "blocks/log_jungle",
            "leg": "#seat"
        },
        "transform": "forge:default-block",
        "uvlock": true
    },
    "variants": {
        "facing=north": { "model": "furnish:chair", "y": 270 },
        "facing=south": { "model": "furnish:chair", "y": 90  },
        "facing=east":  { "model": "furnish:chair"           },
        "facing=west":  { "model": "furnish:chair", "y": 180 }
    }
}